{
    "version": "40.64.3",
    "description": "A Windows desktop rapid programming platform",
    "homepage": "https://www.aardio.com/",
    "license": "freeware",
    "url": "https://www.aardio.com/download/ide/aardio.7z",
    "hash": "707364bf58b5f7d6bfcbbcb2714bd359c60244394d06a3670ea976c6a6c1c99c",
    "shortcuts": [
        [
            "aardio.exe",
            "aardio"
        ]
    ],
    "persist": "config\\USR.CFG",
    "checkver": {
        "url": "https://ide.update.aardio.com/log/",
        "regex": "aardio v([\\d\\.]+)"
    },
    "autoupdate": {
        "url": "https://www.aardio.com/download/ide/aardio.7z"
    }
}
