{
    "homepage": "https://landrop.app/",
    "license": "BSD-3-Clause",
    "version": "0.3.0",
    "url": "https://releases.landrop.app/LANDrop-latest-win.zip",
    "hash": "cd4b27d77212731f70cf24d7fbcfd89cb44df060fa66efe7bd3464675afd4be4",
    "extract_dir": "LANDrop",
    "bin": "LANDrop.exe",
    "shortcuts": [
        [
            "LANDrop.exe",
            "LANDrop"
        ]
    ],
    "checkver": {
        "github": "https://github.com/LANDrop/LANDrop"
    },
    "autoupdate": {
        "url": "https://releases.landrop.app/LANDrop-latest-win.zip"
    }
}
